reg4/reg4.v
//module for a 4-bit register with an asynchronous reset (active high)
module reg4(
    input [3:0] D,
    input CLK, RST,
    output reg [3:0] Q
);

always @(posedge CLK or posedge RST) begin
    if(RST)
        Q <= 4'b0000;
    else
        Q <= D;
end

endmodule

reg4/reg4_tb.v
`include "reg4.v"
`timescale 1ns/1ns

module reg4_tb ();

    reg [3:0] D = 4'b0000;
    reg CLK = 0, RST = 0;
    wire [3:0] Q;
    //instantiate register
    reg4 DUT(.D(D), .CLK(CLK), .RST(RST), .Q(Q)); 
    //setup the clock
    always begin
        CLK = ~CLK;
        #10;
    end

    initial begin
        
        $dumpfile("reg4_tb.vcd");
        $dumpvars(0,reg4_tb);

        //Toggle Reset
        RST <= 1'b1;
        #10
        RST <= 1'b0;

        //Increment the value in the Register
        #20
        D <= D + 1;

        #20
        D <= D + 1;

        #20
        D <= D + 1;

        #20
        D <= D + 1;

        //Hit Reset Again
        #20 
        RST <= 1'b1;
        #10
        RST <= 1'b0;

        #20
        $display("Reg4 Test Done");
        $finish;
    end

endmodule

reg4/reg4_tb.vcd
$date
	Sat Aug 28 22:22:18 2021
$end
$version
	Icarus Verilog
$end
$timescale
	1ns
$end
$scope module reg4_tb $end
$var wire 4 ! Q [3:0] $end
$var reg 1 " CLK $end
$var reg 4 # D [3:0] $end
$var reg 1 $ RST $end
$scope module DUT $end
$var wire 1 " CLK $end
$var wire 4 % D [3:0] $end
$var wire 1 $ RST $end
$var reg 4 & Q [3:0] $end
$upscope $end
$upscope $end
$enddefinitions $end
#0
$dumpvars
b0 &
b0 %
1$
b0 #
1"
b0 !
$end
#10
0$
0"
#20
1"
#30
b1 #
b1 %
0"
#40
b1 !
b1 &
1"
#50
b10 #
b10 %
0"
#60
b10 !
b10 &
1"
#70
b11 #
b11 %
0"
#80
b11 !
b11 &
1"
#90
b100 #
b100 %
0"
#100
b100 !
b100 &
1"
#110
b0 !
b0 &
1$
0"
#120
0$
1"
#130
0"
#140
b100 !
b100 &
1"
